{
    "key": "group_6516e205523ea",
    "title": "Projects",
    "fields": [
        {
            "key": "field_6517032edb8f3",
            "label": "Project Description",
            "name": "project_description",
            "aria-label": "",
            "type": "wysiwyg",
            "instructions": "",
            "required": 0,
            "conditional_logic": 0,
            "wrapper": {
                "width": "",
                "class": "",
                "id": ""
            },
            "default_value": "",
            "tabs": "all",
            "toolbar": "full",
            "media_upload": 1,
            "delay": 0
        },
        {
            "key": "field_6516e206684eb",
            "label": "Students",
            "name": "students",
            "aria-label": "",
            "type": "repeater",
            "instructions": "",
            "required": 0,
            "conditional_logic": 0,
            "wrapper": {
                "width": "",
                "class": "",
                "id": ""
            },
            "layout": "block",
            "pagination": 0,
            "min": 0,
            "max": 0,
            "collapsed": "",
            "button_label": "Add Student",
            "rows_per_page": 20,
            "sub_fields": [
                {
                    "key": "field_6516e22a684ec",
                    "label": "Student Name",
                    "name": "student_name",
                    "aria-label": "",
                    "type": "text",
                    "instructions": "",
                    "required": 0,
                    "conditional_logic": 0,
                    "wrapper": {
                        "width": "80",
                        "class": "",
                        "id": ""
                    },
                    "default_value": "",
                    "maxlength": "",
                    "placeholder": "",
                    "prepend": "",
                    "append": "",
                    "parent_repeater": "field_6516e206684eb"
                },
                {
                    "key": "field_6516e233684ed",
                    "label": "Class of",
                    "name": "class_of",
                    "aria-label": "",
                    "type": "text",
                    "instructions": "",
                    "required": 0,
                    "conditional_logic": 0,
                    "wrapper": {
                        "width": "20",
                        "class": "",
                        "id": ""
                    },
                    "default_value": "",
                    "maxlength": "",
                    "placeholder": "",
                    "prepend": "",
                    "append": "",
                    "parent_repeater": "field_6516e206684eb"
                },
                {
                    "key": "field_6516e259684ee",
                    "label": "Photo",
                    "name": "photo",
                    "aria-label": "",
                    "type": "image",
                    "instructions": "",
                    "required": 0,
                    "conditional_logic": 0,
                    "wrapper": {
                        "width": "",
                        "class": "",
                        "id": ""
                    },
                    "return_format": "array",
                    "library": "all",
                    "min_width": "",
                    "min_height": "",
                    "min_size": "",
                    "max_width": "",
                    "max_height": "",
                    "max_size": "",
                    "mime_types": "",
                    "preview_size": "medium",
                    "parent_repeater": "field_6516e206684eb"
                }
            ]
        },
        {
            "key": "field_6517035fdb8f4",
            "label": "Link to more information",
            "name": "link",
            "aria-label": "",
            "type": "url",
            "instructions": "",
            "required": 0,
            "conditional_logic": 0,
            "wrapper": {
                "width": "",
                "class": "",
                "id": ""
            },
            "default_value": "",
            "placeholder": ""
        },
        {
            "key": "field_651704ada2825",
            "label": "Year awarded",
            "name": "year_awarded",
            "aria-label": "",
            "type": "taxonomy",
            "instructions": "",
            "required": 0,
            "conditional_logic": 0,
            "wrapper": {
                "width": "",
                "class": "",
                "id": ""
            },
            "taxonomy": "award-year",
            "add_term": 1,
            "save_terms": 1,
            "load_terms": 1,
            "return_format": "object",
            "field_type": "select",
            "allow_null": 1,
            "bidirectional": 0,
            "multiple": 0,
            "bidirectional_target": []
        }
    ],
    "location": [
        [
            {
                "param": "post_type",
                "operator": "==",
                "value": "project"
            }
        ]
    ],
    "menu_order": -10,
    "position": "normal",
    "style": "default",
    "label_placement": "top",
    "instruction_placement": "label",
    "hide_on_screen": [
        "the_content"
    ],
    "active": true,
    "description": "",
    "show_in_rest": 0,
    "modified": 1696007565
}
